mctools/__init__.py
mctools/__main__.py
mctools/async_mclient.py
mctools/async_protocol.py
mctools/encoding.py
mctools/errors.py
mctools/formattertools.py
mctools/mclient.py
mctools/packet.py
mctools/protocol.py
mctools-1.4.1.dist-info/licenses/LICENSE
mctools-1.4.1.dist-info/METADATA
mctools-1.4.1.dist-info/WHEEL
mctools-1.4.1.dist-info/entry_points.txt
mctools-1.4.1.dist-info/top_level.txt
mctools-1.4.1.dist-info/RECORD
