Metadata-Version: 2.4
Name: mctools
Version: 1.4.1
Summary: Python implementations of common Minecraft protocols.
Author-email: Owen Cochell <owencochell@hotmail.com>
License: MIT License
Project-URL: Documentation, https://mctools.readthedocs.io/
Project-URL: Repository, https://github.com/Owen-Cochell/mctools
Project-URL: Issues, https://github.com/Owen-Cochell/mctools/issues
Keywords: minecraft,rcon,query,ping,server list ping
Classifier: Development Status :: 5 - Production/Stable
Classifier: Intended Audience :: Developers
Classifier: Topic :: Software Development :: Libraries
Classifier: License :: OSI Approved :: MIT License
Classifier: Programming Language :: Python :: 3 :: Only
Classifier: Programming Language :: Python :: 3.6
Classifier: Programming Language :: Python :: 3.7
Classifier: Programming Language :: Python :: 3.8
Classifier: Programming Language :: Python :: 3.9
Classifier: Programming Language :: Python :: 3.10
Classifier: Programming Language :: Python :: 3.11
Classifier: Programming Language :: Python :: 3.12
Requires-Python: <4,>=3.6
License-File: LICENSE
Provides-Extra: color
Requires-Dist: colorama; extra == "color"
Dynamic: license-file
